MANIFEST.in
README.rst
README.txt
plonetheme.unam.zip
screenshot-cel.png
screenshot-cel2.png
setup.py
docs/CHANGES.txt
docs/CONTRIBUTORS.txt
src/plonetheme/__init__.py
src/plonetheme.unam.egg-info/PKG-INFO
src/plonetheme.unam.egg-info/SOURCES.txt
src/plonetheme.unam.egg-info/dependency_links.txt
src/plonetheme.unam.egg-info/entry_points.txt
src/plonetheme.unam.egg-info/namespace_packages.txt
src/plonetheme.unam.egg-info/not-zip-safe
src/plonetheme.unam.egg-info/requires.txt
src/plonetheme.unam.egg-info/top_level.txt
src/plonetheme/unam/__init__.py
src/plonetheme/unam/configure.zcml
src/plonetheme/unam/testing.py
src/plonetheme/unam/tests/__init__.py
src/plonetheme/unam/tests/test_theme.py
src/plonetheme/unam/theme/.DS_Store
src/plonetheme/unam/theme/plonetheme.unam/.DS_Store
src/plonetheme/unam/theme/plonetheme.unam/index.html
src/plonetheme/unam/theme/plonetheme.unam/manifest.cfg
src/plonetheme/unam/theme/plonetheme.unam/preview.png
src/plonetheme/unam/theme/plonetheme.unam/rules.xml
src/plonetheme/unam/theme/plonetheme.unam/static/.DS_Store
src/plonetheme/unam/theme/plonetheme.unam/static/favicon.ico
src/plonetheme/unam/theme/plonetheme.unam/static/function.js
src/plonetheme/unam/theme/plonetheme.unam/static/matem-logo.png
src/plonetheme/unam/theme/plonetheme.unam/static/matem-logo2.png
src/plonetheme/unam/theme/plonetheme.unam/static/search-ico.png
src/plonetheme/unam/theme/plonetheme.unam/static/sections-ico.png
src/plonetheme/unam/theme/plonetheme.unam/static/style.css
src/plonetheme/unam/theme/plonetheme.unam/static/touch_icon.png
src/plonetheme/unam/theme/plonetheme.unam/static/unam-logo.png