Metadata-Version: 1.1
Name: plonetheme.unam
Version: 0.1
Summary: A responsive theme that provides a nice unam.mx like HTML output
Home-page: https://github.com/imatem/plonetheme.unam
Author: Gildardo Bautista
Author-email: gil.cano@gmail.com
License: GPL
Platform: Any
Classifier: Environment :: Web Environment
Classifier: Framework :: Plone
Classifier: Intended Audience :: Developers
Classifier: License :: OSI Approved :: GNU General Public License (GPL)
Classifier: Operating System :: OS Independent
Classifier: Programming Language :: Python
